torchmoon/__init__.py
torchmoon/__main__.py
torchmoon/__version__.py
torchmoon/hyperparameter.py
torchmoon/logger.py
torchmoon/training.py
torchmoon/datamodules/__init__.py
torchmoon/datamodules/deepcraterdata.py
torchmoon/model/__init__.py
torchmoon/model/cratervnet.py
torchmoon/model/deepmoon.py
torchmoon/torch/__init__.py
torchmoon/torch/activations.py
torchmoon/torch/conv.py
torchmoon/torch/util.py
torchmoon-1.0.4.dist-info/METADATA
torchmoon-1.0.4.dist-info/WHEEL
torchmoon-1.0.4.dist-info/top_level.txt
torchmoon-1.0.4.dist-info/RECORD
